consenrich/__init__.py
consenrich/cconsenrich.c
consenrich/cconsenrich.cpython-311-x86_64-linux-gnu.so
consenrich/cconsenrich.pyx
consenrich/consenrich.py
consenrich/constants.py
consenrich/core.py
consenrich/detrorm.py
consenrich/matching.py
consenrich/misc_util.py
consenrich/data/ce10.sizes
consenrich/data/ce10_blacklist.bed
consenrich/data/ce10_sparse.bed
consenrich/data/ce11.sizes
consenrich/data/ce11_blacklist.bed
consenrich/data/ce11_sparse.bed
consenrich/data/dm6.sizes
consenrich/data/dm6_blacklist.bed
consenrich/data/dm6_sparse.bed
consenrich/data/hg19.sizes
consenrich/data/hg19_blacklist.bed
consenrich/data/hg19_sparse.bed
consenrich/data/hg38.sizes
consenrich/data/hg38_blacklist.bed
consenrich/data/hg38_sparse.bed
consenrich/data/mm10.sizes
consenrich/data/mm10_blacklist.bed
consenrich/data/mm10_sparse.bed
consenrich/data/mm39.sizes
consenrich/data/mm39_blacklist.bed
consenrich/data/mm39_sparse.bed
consenrich.libs/libgomp-e985bcbb.so.1.0.0
consenrich-0.8.12rc1.dist-info/METADATA
consenrich-0.8.12rc1.dist-info/WHEEL
consenrich-0.8.12rc1.dist-info/entry_points.txt
consenrich-0.8.12rc1.dist-info/top_level.txt
consenrich-0.8.12rc1.dist-info/RECORD
consenrich-0.8.12rc1.dist-info/licenses/LICENSE
