Metadata-Version: 2.4
Name: consenrich
Version: 0.8.12rc1
Summary: Genome-wide estimation of signals hidden in noisy multi-sample HTS datasets
Author-email: "Nolan H. Hamilton" <nolan.hamilton@unc.edu>
Requires-Python: >=3.11
License-File: LICENSE
Requires-Dist: cython>=3.0
Requires-Dist: numpy>=2.1
Requires-Dist: scipy>=1.15
Requires-Dist: pandas>=2.3.0
Requires-Dist: pysam>=0.23.3
Requires-Dist: pybedtools>=0.11.2
Requires-Dist: PyYAML>=6.0.2
Requires-Dist: PyWavelets>=1.9.0
Requires-Dist: matplotlib
Requires-Dist: tqdm
Requires-Dist: itrigamma>=0.1.0a
Provides-Extra: dev
Requires-Dist: pytest; extra == "dev"
Requires-Dist: mypy; extra == "dev"
Requires-Dist: ruff; extra == "dev"
Requires-Dist: build; extra == "dev"
Requires-Dist: twine; extra == "dev"
Provides-Extra: docs
Requires-Dist: sphinx>=7.3; extra == "docs"
Requires-Dist: sphinx-press-theme; extra == "docs"
Requires-Dist: furo; extra == "docs"
Requires-Dist: myst-parser>=2.0; extra == "docs"
Requires-Dist: sphinx-autodoc-typehints>=2.1; extra == "docs"
Requires-Dist: sphinx-autobuild>=2025.2; extra == "docs"
Requires-Dist: sphinx-copybutton>=0.5.0; extra == "docs"
Requires-Dist: sphinxcontrib-bibtex>=2.4.0; extra == "docs"
Provides-Extra: plot
Requires-Dist: plotext; extra == "plot"
Requires-Dist: seaborn; extra == "plot"
Requires-Dist: matplotlib; extra == "plot"
Dynamic: license-file
Dynamic: requires-python
